{
  "version": 1,
  "project": "ultraplan-go",
  "sprint": "21-plan-stage",
  "updatedAt": "2026-06-15T18:24:01.706Z",
  "stages": {
    "requirements": {
      "status": "complete",
      "path": "requirements.md",
      "lastRunAt": "2026-06-15T18:08:10.185Z"
    },
    "sprint-index": {
      "status": "complete",
      "path": "sprint-index.md",
      "lastRunAt": "2026-06-15T18:10:58.338Z"
    },
    "technical-handbook": {
      "status": "complete",
      "path": "technical-handbook.md",
      "lastRunAt": "2026-06-15T18:14:02.820Z"
    },
    "area-reasoning": {
      "status": "skipped",
      "path": "reasoning/",
      "lastRunAt": "2026-06-15T18:04:26.616Z"
    },
    "reasoning": {
      "status": "complete",
      "path": "reasoning.md",
      "lastRunAt": "2026-06-15T18:19:12.012Z"
    },
    "plan": {
      "status": "complete",
      "path": "plan.md",
      "lastRunAt": "2026-06-15T18:24:01.706Z"
    },
    "implementation": {
      "status": "missing",
      "path": ".run-state.json"
    },
    "review": {
      "status": "missing",
      "path": "review.md"
    }
  }
}